{
    "annotations": {
      "list": [
        {
          "builtIn": 1,
          "datasource": {
            "type": "grafana",
            "uid": "-- Grafana --"
          },
          "enable": true,
          "hide": true,
          "iconColor": "rgba(0, 211, 255, 1)",
          "name": "Annotations & Alerts",
          "type": "dashboard"
        }
      ]
    },
    "editable": true,
    "fiscalYearStartMonth": 0,
    "graphTooltip": 0,
    "id": 7,
    "links": [],
    "panels": [
      {
        "datasource": {
          "type": "prometheus",
          "uid": "aeh1vqabhvg1sf"
        },
        "fieldConfig": {
          "defaults": {
            "color": {
              "mode": "palette-classic"
            },
            "custom": {
              "axisBorderShow": true,
              "axisCenteredZero": false,
              "axisColorMode": "text",
              "axisGridShow": true,
              "axisLabel": "Quality rate, %",
              "axisPlacement": "auto",
              "barAlignment": 0,
              "barWidthFactor": 0.6,
              "drawStyle": "line",
              "fillOpacity": 0,
              "gradientMode": "none",
              "hideFrom": {
                "legend": false,
                "tooltip": false,
                "viz": false
              },
              "insertNulls": false,
              "lineInterpolation": "smooth",
              "lineWidth": 1,
              "pointSize": 3,
              "scaleDistribution": {
                "type": "linear"
              },
              "showPoints": "auto",
              "spanNulls": false,
              "stacking": {
                "group": "A",
                "mode": "none"
              },
              "thresholdsStyle": {
                "mode": "off"
              }
            },
            "fieldMinMax": false,
            "mappings": [],
            "max": 1,
            "thresholds": {
              "mode": "absolute",
              "steps": [
                {
                  "color": "green",
                  "value": null
                },
                {
                  "color": "red",
                  "value": 80
                }
              ]
            },
            "unit": "percentunit"
          },
          "overrides": []
        },
        "gridPos": {
          "h": 8,
          "w": 12,
          "x": 0,
          "y": 0
        },
        "id": 1,
        "options": {
          "legend": {
            "calcs": [],
            "displayMode": "list",
            "placement": "bottom",
            "showLegend": true
          },
          "tooltip": {
            "mode": "single",
            "sort": "none"
          }
        },
        "pluginVersion": "11.3.0",
        "targets": [
          {
            "datasource": {
              "type": "prometheus",
              "uid": "aeh1vqabhvg1sf"
            },
            "disableTextWrap": false,
            "editorMode": "builder",
            "expr": "eas_quality_rate_persents",
            "fullMetaSearch": false,
            "includeNullMetadata": true,
            "instant": false,
            "legendFormat": "cluster{{cluster}}",
            "range": true,
            "refId": "A",
            "useBackend": false
          }
        ],
        "title": "EAS quality rate",
        "type": "timeseries"
      }
    ],
    "preload": false,
    "refresh": "1m",
    "schemaVersion": 40,
    "tags": [],
    "templating": {
      "list": []
    },
    "time": {
      "from": "now-15m",
      "to": "now"
    },
    "timepicker": {},
    "timezone": "browser",
    "title": "EAS",
    "uid": "aem26bhucbke8f",
    "version": 4,
    "weekStart": ""
  }